NutMaat/__init__.py
NutMaat/_version.py
NutMaat/classifier.py
NutMaat/encoding.py
NutMaat/evaluate.py
NutMaat/library.py
NutMaat/peculiarities.py
NutMaat/preprocessing.py
NutMaat/spectrum.py
NutMaat/utils.py
NutMaat-0.1.1.dist-info/LICENSE.txt
NutMaat-0.1.1.dist-info/METADATA
NutMaat-0.1.1.dist-info/WHEEL
NutMaat-0.1.1.dist-info/top_level.txt
NutMaat-0.1.1.dist-info/RECORD
