Metadata-Version: 2.1
Name: NutMaat
Version: 0.1.1
Summary: A Python library for classifying stellar spectra based on the MKCLASS package
Home-page: https://github.com/rehamelkholy/NutMaat
Author: Reham El-Kholy, PhD
Author-email: reham.elkholy@cu.edu.eg
License: MIT
Classifier: Programming Language :: Python :: 3
Classifier: License :: OSI Approved :: MIT License
Classifier: Operating System :: OS Independent
Classifier: Development Status :: 4 - Beta
Requires-Python: >=3.9
License-File: LICENSE.txt
Requires-Dist: numpy>=2.0.0
Requires-Dist: pandas==2.2.2
Requires-Dist: scipy>=1.14.0
Requires-Dist: tqdm>=4.66.5
